{
  "_comment": [
    "카드별 hand-curated expected value — 정량 환산 어려운 카드의 fallback.",
    "EffectValueCatalog 가 vars 환산 못 하는 카드 (NamedPower 마커, vars 없음, conditional 등)",
    "에 대해 명시적 dmg equivalent 값 제공.",
    "",
    "_unit: 1 use 의 dmg equivalent (Power 는 5 turn 누적, 즉발 카드는 단일 use 가치).",
    "_baseline_turns: 5 turn (act2 mid, effect_value_table 와 일관).",
    "phase factor 는 Stage2Scorer 가 외부 적용 — value 자체는 평균.",
    "",
    "선택 필드 ceiling/ceiling_basis — archetype 빌드 활성 시 5턴+ 전투 현실 상한 (참고용 기록).",
    "현재 추천 파이프라인은 baseline value 만 사용. 향후 활성도 측정이 정교해지면 보간 도입 예정.",
    "ceiling 미정의 카드는 baseline 만 측정 (천장 효과 미미하거나 미평가).",
    "",
    "Top ~30 IRONCLAD/SHARED/REGENT/SILENT/DEFECT 카드. 추가 보강은 incremental."
  ],
  "_unit": "dmg_equivalent (1 use, 5 turn 누적 가정)",
  "_ceiling_unit": "dmg_equivalent (archetype 활성, 8 turn 가정)",

  "cards": {
    "INFLAME":         {"value": 10, "basis": "+2 STR × 5 후속 attacks (1회 즉발)"},
    "DEMON_FORM":      {"value": 25, "ceiling": 50, "basis": "+2 STR/turn cumulative — (1+2+3+4) × 2 × 4 atk avg / 적용 지연 보정", "ceiling_basis": "8턴 boss — STR (2+4+6+8+10+12+14) × 5 atk avg, energy 보강 + 풀 ramp"},
    "INFERNO":         {"value": 28, "basis": "self_damage 6/turn × 5 turn × hit chance ~0.95"},
    "ROLLING_BOULDER": {"value": 35, "ceiling": 65, "basis": "Increment 5 × triangular (5+6+7+8+9) = 35 - some loss", "ceiling_basis": "8턴 ramp (5+6+...+12) = 68 — STR/취약 부착 시 dmg eq +20%"},
    "JUGGERNAUT":      {"value": 18, "basis": "5 dmg × 4 block plays (random target loss)"},
    "BARRICADE":       {"value": 25, "ceiling": 55, "basis": "block 영구 cumulative × 5 turn — block_avg 7 × 4 turn carry-over", "ceiling_basis": "Defender 빌드 8턴 boss — block_avg 10 × 7 turn carry-over, Body Slam 등 페이오프 동반 시"},
    "AFTERIMAGE":      {"value": 16, "ceiling": 35, "basis": "1 block × 4 cards/turn × 4 turn", "ceiling_basis": "DRAW-heavy 8턴 — 1 block × 6 cards/turn × 7 turn = 42, deck cycling 시"},
    "CRIMSON_MANTLE":  {"value": 12, "basis": "Block 8 + innate bonus +1.5x"},
    "ARSENAL":         {"value": 12, "basis": "+1 STR/turn cumulative × 4 atk"},
    "DARK_EMBRACE":    {"value": 14, "ceiling": 32, "basis": "draw 1 × 3 exhausts × 4 dmg eq/draw + bonus", "ceiling_basis": "EXHAUST 빌드 8턴 — 1 draw × 8 exhausts × 4 dmg eq + Feel No Pain 시너지"},
    "FEEL_NO_PAIN":    {"value": 10, "basis": "block 3 × 3 exhaust events"},
    "CORRUPTION":      {"value": 22, "ceiling": 45, "basis": "skill cost 0 — 평균 5 cost saved × 4 dmg/cost", "ceiling_basis": "skill-heavy 빌드 8턴 — 8 skills cost 0 × 5~6 dmg/cost saved + EXHAUST_TARGET 시너지"},
    "BRUTALITY":       {"value": 18, "ceiling": 40, "basis": "+1 STR/turn cumulative + draw 1/turn", "ceiling_basis": "8턴 ramp (1+2+...+7) × 4 atk + draw 7장 보강 — HpLoss 회복 가능 시"},
    "BULLET_TIME":     {"value": 14, "basis": "skill cost 0 1 turn — 5 skills × ~3 dmg eq"},
    "METALLICIZE":     {"value": 15, "ceiling": 30, "basis": "block 3/turn × 5 turn", "ceiling_basis": "Defender 8턴 boss — block 3/turn × 8 + Body Slam 시너지 + carry 보강"},
    "COMBUST":         {"value": 18, "ceiling": 38, "basis": "self damage 5 dmg/turn + AOE potential", "ceiling_basis": "8턴 mob (3 적) — 5 dmg AOE × 8 × 0.9 = 108 - self_dmg cost ~25"},
    "DOPPELGANGER":    {"value": 10, "basis": "+X energy + draw — variable, average"},

    "BLACK_HOLE":      {"value": 18, "basis": "AOE 3 × multi enemy + STAR_PRODUCER 보강"},
    "CHILD_OF_THE_STARS": {"value": 12, "basis": "block 2 per star × 4 stars + STAR_PAYOFF"},
    "GLOW":            {"value": 8,  "basis": "STAR 1 + Damage burst small"},
    "VENERATE":        {"value": 14, "basis": "STAR_BURST 3 stars + draw"},
    "STARDUST":        {"value": 12, "basis": "X-cost AOE — variable, average use"},
    "RADIATE":         {"value": 10, "basis": "STAR_PRODUCER + small AOE"},
    "GENESIS":         {"value": 16, "basis": "STAR_BURST 큼 cost 2"},

    "ACCURACY":        {"value": 16, "basis": "+4 dmg per shiv × 4 shivs/combat"},
    "ENVENOM":         {"value": 20, "ceiling": 50, "basis": "Poison 1 per attack × 5 attacks/turn × 5 turn (light scaling)", "ceiling_basis": "POISON 빌드 8턴 — multi-hit attack (DAGGER_SPRAY 등) × 8 turn 누적 stacks"},
    "NOXIOUS_FUMES":   {"value": 25, "ceiling": 60, "basis": "Poison 2/turn cumulative — triangular", "ceiling_basis": "POISON 빌드 8턴 — stacks (2+4+6+8+10+12+14+16) × triangular tick - decay"},
    "INFINITE_BLADES": {"value": 14, "ceiling": 32, "basis": "Shiv 1/turn × 4 turn × 4 dmg eq", "ceiling_basis": "SHIV/CUNNING 빌드 8턴 — Shiv 1/turn × 8 × 4 dmg + ACCURACY/AMPLIFIER 시너지"},

    "ECHO_FORM":       {"value": 18, "ceiling": 50, "basis": "Repeat 1 attack/turn × 5 turn × 6 avg dmg / 2 (penalty)", "ceiling_basis": "8턴 attack-heavy + 큰 attack (Bludgeon 等) — 1 repeat × 8 × 10 dmg avg / 1.5"},
    "LOOP":            {"value": 14, "ceiling": 30, "basis": "frost orb evoke × 5 turn", "ceiling_basis": "FROST/ORB 빌드 8턴 — frost orb evoke × 8 turn × focus 보강"},
    "BIASED_COGNITION": {"value": 16, "ceiling": 35, "basis": "+4 focus burst — orb dmg × 5 turn", "ceiling_basis": "ORB-heavy 빌드 8턴 — focus +4 × orb 다양성 (DARK/FROST/PLASMA) × 8 turn"},
    "CAPACITOR":       {"value": 12, "basis": "+2 orb slot — orb gain × turn"},
    "COOLANT":         {"value": 14, "ceiling": 30, "basis": "block 2 per frost × 5 frosts/combat + orb", "ceiling_basis": "FROST 빌드 8턴 — 2 block × 10+ frosts evoke + orb gain 보강"},

    "APOTHEOSIS":      {"value": 30, "ceiling": 55, "basis": "전체 카드 upgrade × 평균 +3 dmg/card × 8 cards", "ceiling_basis": "act3 진입 deck 15+장 × +3 평균 dmg/card 영구 — 잔여 act 전투 누적"},
    "BEACON_OF_HOPE":  {"value": 14, "basis": "block 12 + innate"},
    "ALCHEMIZE":       {"value": 12, "basis": "random potion × 0.7 use"},
    "PANACHE":         {"value": 18, "basis": "AOE 10 every 5 cards"},
    "SIGNAL_BOOST":    {"value": 16, "basis": "POWER_AMPLIFIER 보강 + cumulative"},
    "DOOM":            {"value": 0, "_basis_phase": true, "_note": "phase 후반에 boss HP threshold — kind=doom 별도 분기"},
    "VOID_FORM":       {"value": 28, "ceiling": 55, "basis": "stars/turn cumulative — STAR_BURST scaling", "ceiling_basis": "REGENT STAR 빌드 8턴 — stars/turn cumulative (1+2+...+7) × consumer 효율"},
    "STORM":           {"value": 18, "ceiling": 40, "basis": "lightning orb 1/turn cumulative + ORB_VARIETY", "ceiling_basis": "DEFECT ORB 빌드 8턴 — lightning orb 1/turn × 8 + Power play trigger 누적"},
    "PHANTOM_BLADES":  {"value": 16, "basis": "Shiv 2/turn × 5 turn × 4 dmg"},
    "AGGRESSION":      {"value": 16, "basis": "재발동 + DAMAGE_AMPLIFIER 보강"},

    "ACCELERANT":      {"value": 14, "ceiling": 35, "basis": "Poison 1 trigger amplifier × poison plays", "ceiling_basis": "POISON 빌드 활성 — 1 trigger × 8 poison plays × 4 dmg eq, NOXIOUS_FUMES + ENVENOM 동반"},
    "PILLAR_OF_CREATION": {"value": 24, "ceiling": 45, "basis": "STAR_PRODUCER 4 stars + scaling", "ceiling_basis": "REGENT STAR 빌드 — 4 stars × consumer 효율 (VENERATE/GENESIS) × 누적 scaling"},
    "DRUM_OF_BATTLE":  {"value": 22, "ceiling": 45, "basis": "Exhaust passive + STR scaling combo", "ceiling_basis": "FORGE/STR 빌드 8턴 — exhaust 카드 × FORGE_AMPLIFIER + STR per-attack 누적"},
    "SPEEDSTER":       {"value": 18, "basis": "energy gain × 5 turn × cost saved"},
    "ARMAMENTS":       {"value": 12, "basis": "block 5 + upgrade 1 hand card avg"},
    "DARK_FOG":        {"value": 16, "basis": "Vuln + AOE small + DRAW_ON_DRAW"},

    "_amplifier_comment": "Amplifier 카드 — 다른 카드 효과 증폭. deck 평균 가정으로 정적 EV 추정. enabler 부족 deck 에선 axisDependencyPenalty 가 별도 차감.",

    "CRUELTY":         {"value": 12, "basis": "VULN_AMPLIFIER 25% — VULN 적 받는 dmg ×1.25 × 8 평균 × 5 turn × 0.6 coverage"},
    "UNMOVABLE":       {"value": 25, "basis": "BLOCK_AMPLIFIER — 매 턴 첫 block ×2 — block_avg 6 × 5 turn × 0.83"},
    "BLUR":            {"value": 14, "basis": "BLOCK_AMPLIFIER — block 다음 턴 유지 — block_avg × 4 turn × 0.7"},
    "ENTRENCH":        {"value": 18, "basis": "BLOCK_AMPLIFIER — block 즉발 ×2 (cost 2 limit)"},
    "BULLY":           {"value": 10, "basis": "VULN_AMPLIFIER cost 0 — 0.25 × 8 dmg × 5 turn × 0.5 coverage"},
    "COLOSSUS":        {"value": 14, "basis": "VULN_AMPLIFIER + ColossusPower self 50% dmg reduction"},
    "DOMINATE":        {"value": 14, "basis": "VULN_AMPLIFIER cost 1"},
    "DEBILITATE":      {"value": 18, "basis": "VULN_AMPLIFIER + WEAK_AMPLIFIER 둘 다"},
    "DISMANTLE":       {"value": 14, "basis": "VULN_AMPLIFIER 지속 효과"},
    "DUAL_WIELD":      {"value": 14, "basis": "POWER_AMPLIFIER — Power 카드 1장 ×2 사용"},
    "FAN_OF_KNIVES":   {"value": 16, "basis": "SHIV_AMPLIFIER + AOE dmg"},
    "FASTEN":          {"value": 10, "basis": "DEFEND_TYPE_AMPLIFIER — Defend ×2 효율"},
    "FLANKING":        {"value": 14, "basis": "DAMAGE_AMPLIFIER cost 2"},
    "HANG":            {"value": 14, "basis": "DAMAGE_AMPLIFIER cost 1"},
    "KNOCKDOWN":       {"value": 18, "basis": "DAMAGE_AMPLIFIER cost 3"},
    "BEAT_INTO_SHAPE": {"value": 14, "basis": "FORGE_AMPLIFIER — forge 카드 효율"},
    "HAMMER_TIME":     {"value": 16, "basis": "FORGE_AMPLIFIER cost 2"},
    "CONQUEROR":       {"value": 16, "basis": "LORDS_BLADE_AMPLIFIER — forge 강화"},
    "COMPILE_DRIVER":  {"value": 14, "basis": "ORB_VARIETY_AMPLIFIER — orb 다양성 보너스"},
    "DARKNESS":        {"value": 16, "ceiling": 35, "basis": "DARK_ORB_AMPLIFIER — dark orb scaling", "ceiling_basis": "DARK_ORB 빌드 — dark orb 누적 charge × focus 보강 × 8턴 evoke"},

    "_misc_comment": "기타 vars 환산 어려운 카드 (Pattern C / vars 없음 / 조건부) — 추정값",

    "WELL_LAID_PLANS":     {"value": 8,  "basis": "Retain 1 — 1 carry × 5 turn × 0.7 use rate"},
    "SNEAKY":              {"value": 14, "basis": "block + CUNNING_PRODUCER + 매 turn trigger"},
    "HIDDEN_GEM":          {"value": 18, "basis": "Replay 2 — 1 attack × 2 use × 9 dmg avg"},
    "TOOLS_OF_THE_TRADE":  {"value": 12, "basis": "CUNNING_CONSUMER — discard 1 + draw 1 / turn"},
    "TRACKING":            {"value": 14, "ceiling": 28, "basis": "WEAK 큰 stacks 적용 — debuff power", "ceiling_basis": "tank 적 + 8턴 — WEAK stacks × enemy_dmg/turn × full duration"},
    "DISCOVERY":           {"value": 12, "basis": "random 카드 1 select × 1 use × 8 dmg avg / 0.7 quality"},
    "DISTRACTION":         {"value": 12, "basis": "random duration card pick"},
    "SPLASH":              {"value": 14, "basis": "DURATION + SCALING small AOE"},
    "SCRAWL":              {"value": 16, "basis": "DRAW + EXHAUST 카드 cycle"},
    "MIMIC":               {"value": 14, "basis": "Block calculated × deck context"},
    "HELLO_WORLD":         {"value": 12, "basis": "CARD_GEN per turn × 5 turn × random card avg"},
    "STACK":               {"value": 14, "basis": "DISCARD_PAYOFF block — discard count × 2 block"},
    "PREP_TIME":           {"value": 14, "basis": "PrepTime Retain scaling × 5 turn"},
    "WORSHIP":             {"value": 12, "basis": "Star + Doom small archetype"},
    "REINFORCED_BODY":     {"value": 12, "basis": "block scaling 시작 small"},
    "BLAZING_SLEDGE":      {"value": 16, "ceiling": 35, "basis": "STAR_PRODUCER + Damage scaling", "ceiling_basis": "REGENT STAR 빌드 — Damage scaling × star consumer 시너지 × 8턴 누적"},
    "FALSE_FATE":          {"value": 14, "basis": "DOOM_AMPLIFIER + scaling"},
    "GLITCH":              {"value": 14, "basis": "ORB random + DRAW"},
    "OUTBREAK":            {"value": 18, "basis": "Repeat 3 + AOE Poison spread"},
    "WHIRLWIND":           {"value": 18, "basis": "X-cost AOE — energy_max × 5 dmg"},

    "_conditional_comment": "강한 조건부 / 일회성 카드 — axes-fallback 의 단순 식으론 못 잡음. 진짜 mechanic 추정 hand-curate.",

    "CALCULATED_GAMBLE":   {"value": 16, "basis": "discard all (~5) + draw all (~5) — discard archetype synergy"},
    "ENLIGHTENMENT":       {"value": 18, "basis": "다음 턴 모든 카드 cost 1 — 5 카드 × ~3 cost 절감 평균"},
    "WISH":                {"value": 14, "basis": "3 wishes × 5 random effect 평균"},
    "SECRET_TECHNIQUE":    {"value": 12, "basis": "UNLIMITED retain skill — search + retain"},
    "SECRET_WEAPON":       {"value": 12, "basis": "UNLIMITED retain attack — search + retain"},
    "OBLIVION":            {"value": 14, "basis": "DOOM 즉시 trigger AOE — boss HP threshold"},
    "MAYHEM":              {"value": 14, "ceiling": 32, "basis": "random POWER replay — 5 turn 누적", "ceiling_basis": "POWER-heavy 빌드 8턴 — random Power replay × 8 turn 누적, top deck draw bias"},
    "CORROSIVE_WAVE":      {"value": 14, "basis": "AOE Poison 2~3 + DRAW_CONDITIONAL"},
    "THE_BOMB":            {"value": 16, "basis": "AOE 40 dmg (3 turn delay × random hit)"},
    "MASTER_PLANNER":      {"value": 16, "basis": "CUNNING_PRODUCER + SKILL_CONDITIONAL — discard + draw"},
    "ANOINTED":            {"value": 12, "basis": "DRAW_PILE_SEARCH + CARD_RETURN — exhaust 보강"},
    "STRATAGEM":           {"value": 12, "basis": "DRAW_PILE_SEARCH + CARD_RETURN power 형식"},
    "STORM_OF_STEEL":      {"value": 14, "ceiling": 32, "basis": "CUNNING_CONSUMER — discard 후 shiv 생성", "ceiling_basis": "SHIV/CUNNING 빌드 — full hand discard × shiv 7장 × ACCURACY 보강"},
    "DEMONIC_SHIELD":      {"value": 12, "basis": "block calc + HpLoss 1 — exhaust 일회성"},
    "PRIMAL_FORCE":        {"value": 14, "basis": "CARD_GEN + DAMAGE — energy 보강"},
    "GLITCH":              {"value": 14, "basis": "ORB random + DRAW (이미 있는데 misc 분류)"},
    "PHANTASMAL":          {"value": 14, "basis": "DAMAGE_AMPLIFIER 다음 턴 ×2 — single trigger"},
    "BURST":               {"value": 12, "basis": "Skills 1 — replay 다음 skill"},
    "ALIGNMENT":           {"value": 12, "basis": "ENERGY 보강 + REGENT 별 cost 보강"},
    "REAPER_FORM":         {"value": 16, "ceiling": 35, "basis": "DOOM_PRODUCER 영구 — turn마다 doom stack", "ceiling_basis": "DOOM 빌드 + 8턴 boss — doom stacks (1+2+...+7) × HP threshold trigger"},
    "END_OF_DAYS":         {"value": 18, "basis": "AOE_DOOM 즉시 trigger — large effect"},

    "_trigger_power_comment": "Trigger / Per-event Power 카드 — vars 단순 환산이 *trigger 누적* 못 잡음. 5 turn × trigger rate × effect.",

    "VICIOUS":             {"value": 16, "ceiling": 32, "basis": "VULN 부여 매 trigger draw 1 — 5 turn × 1.5 VULN apply × 2.5 dmg eq/draw", "ceiling_basis": "VULN 빌드 8턴 — 8 turn × 2+ VULN apply/turn × 3 dmg eq/draw + cycling"},
    "PAGESTORM":           {"value": 14, "basis": "Per-event Cards 1 trigger × 5 turn"},
    "HELLRAISER":          {"value": 16, "ceiling": 35, "basis": "지옥검무 — strike per-draw trigger", "ceiling_basis": "DRAW-heavy 빌드 8턴 — strike per draw × 6+ draws/turn × 8 turn 누적"},
    "CALAMITY":            {"value": 14, "basis": "PLAY_TRIGGER attack 보강 × 5 turn"},
    "SLEIGHT_OF_FLESH":    {"value": 16, "basis": "PLAY_TRIGGER + DEBUFF_APPLY_TRIGGER 누적 9 stacks"},
    "THE_SEALED_THRONE":   {"value": 14, "basis": "PLAY_TRIGGER STAR_BURST 누적"},
    "BODY_SLAM":           {"value": 12, "basis": "block 만큼 dmg — 평균 block 6 × use 1.5 = 9~12"},
    "KINGLY_PUNCH":        {"value": 14, "basis": "Damage 8 + Increase 4 누적"},
    "AUTOMATION":          {"value": 12, "basis": "Energy 1 + per-turn card gen"},
    "QUASAR":              {"value": 12, "basis": "별 cost SCALING random"},
    "ARSENAL":             {"value": 14, "ceiling": 30, "basis": "ArsenalPower — STR per-attack scaling 보강", "ceiling_basis": "ATTACK-heavy 8턴 — STR per-attack × 5+ atk/turn × 8 turn 누적"},

    "_calculated_comment": "Calculated/Conditional damage 카드 — vars 가 Pattern C (CalculatedDamage/Hits 등 factor 0). base dmg + 조건 누적 평균 가정 hand-curate.",

    "CONFLAGRATION":       {"value": 18, "ceiling": 38, "basis": "AOE base 8 + (다른 attack 평균 2장 × 2 = 4) × AOE 2 enemies × 1.5 use", "ceiling_basis": "ATTACK-heavy mob 전투 — base 8 + 6 attacks × 2 = 20 × AOE 3 enemies × 1.5 use"},
    "PERFECTED_STRIKE":    {"value": 18, "ceiling": 38, "basis": "base 6 + strike_count 6 × 2 = 18 (deck 의 strike 평균 6장)", "ceiling_basis": "STRIKE-heavy starter 보존 빌드 — base 6 + 12 strikes × 2 = 30, 강화 시 ×2.5"},
    "ASHEN_STRIKE":        {"value": 14, "basis": "base 6 + exhaust_count 3 × 3 = 15 × use 0.9"},
    "DEATH_MARCH":         {"value": 14, "basis": "base 8 + play_count 2 × 3 = 14 cost 1"},
    "MEMENTO_MORI":        {"value": 16, "basis": "base 9 + discard_turn 2 × 4 = 17 cost 1"},
    "PRECISE_CUT":         {"value": 16, "basis": "base 13 cost 0 + extra 2 × small scaling — FREE_ATTACK"},
    "REND":                {"value": 18, "basis": "base 15 + extra 5 × 1 trigger cost 2 use 1.5"},
    "SQUEEZE":             {"value": 22, "ceiling": 45, "basis": "base 25 + extra 5 × osty cost 3 — boss kill potential", "ceiling_basis": "boss 1턴 처치 시나리오 — base 25 + extra 5 × 4 osty + STR/취약 보강 = 60+"},
    "GANG_UP":             {"value": 14, "basis": "base 5 + extra 5/skeleton × 2 skeletons = 15"},
    "MURDER":              {"value": 16, "basis": "scaling base 1 + extra 1 × turn count cost 3"},
    "FINISHER":            {"value": 14, "basis": "Damage 6 × hit_count 2 = 12 cost 1"},
    "FLAK_CANNON":         {"value": 14, "basis": "Damage 8 × hits 1.5 cost 2 + EXHAUST"},
    "FLECHETTES":          {"value": 12, "basis": "Damage 5 × skill_count 2 = 10 cost 1"},
    "HELIX_DRILL":         {"value": 10, "basis": "Damage 3 × hits 2 = 6 cost 0 + EXHAUST"},
    "LUNAR_BLAST":         {"value": 14, "basis": "Damage 4 × hits 2 = 8 cost 0 + COMBO + FREE"},
    "BARRAGE":             {"value": 12, "basis": "Damage 5 × orb_count 2 = 10 cost 1"},
    "MIND_BLAST":          {"value": 10, "basis": "extra 1 × cards 5 = 5 cost 1 + INNATE"},
    "PULL_FROM_BELOW":     {"value": 12, "basis": "Damage 5 × volatile 2 = 10 cost 1"},
    "RATTLE":              {"value": 12, "basis": "OstyDamage 7 × hits 1.5 cost 1"},
    "SOUL_STORM":          {"value": 14, "ceiling": 30, "basis": "base 9 + extra 2 × soul cost 1 + SCALING", "ceiling_basis": "SOUL 빌드 8턴 — base 9 + extra 2 × 8 souls = 25 × use 1.2"},
    "SOVEREIGN_BLADE":     {"value": 14, "basis": "Damage 10 × Repeat 1 + RETAIN cost 2"},
    "SUPERMASSIVE":        {"value": 14, "basis": "base 5 + extra 3 × scaling cost 1"},
    "PROTECTOR":           {"value": 14, "basis": "base 10 + extra 1 × skeleton cost 1"},
    "MIRAGE":              {"value": 12, "basis": "Block calculated × poison + AOE cost 1"},
    "KNIFE_TRAP":          {"value": 14, "ceiling": 30, "basis": "Shivs × scaling cost 2", "ceiling_basis": "SHIV 빌드 8턴 — Shivs scaling × 카드 사용수 누적 × ACCURACY 보강"},

    "_repeat_comment": "Repeat / multi-hit 카드 — effect_value_table 의 Repeat factor 0 으로 vars 환산 무시. Damage × Repeat 식 hand-curate.",

    "STAMPEDE":            {"value": 18, "ceiling": 38, "basis": "쇄도 — 매 턴 random attack × 5 turn × 8 avg dmg / cost 2", "ceiling_basis": "8턴 전투 — random attack × 8 × 10 dmg avg (강한 attack pool) / cost amortize"},
    "SWORD_BOOMERANG":     {"value": 14, "basis": "Damage 3 × Repeat 3 = 9 × use 1.5"},
    "THRASH":              {"value": 14, "basis": "Damage 4 × 2 + extra from absorbed card"},
    "BOUNCING_FLASK":      {"value": 22, "ceiling": 50, "basis": "Poison 3 × Repeat 3 = 9 stacks triangular tick (45 - decay)", "ceiling_basis": "POISON 빌드 8턴 boss — 9 stacks × triangular (9+8+...+2) = 44, multi-cast + STR 보강"},
    "EXTERMINATE":         {"value": 12, "basis": "Damage 3 × Repeat 4 = 12 cost 1"},
    "PECK":                {"value": 8,  "basis": "Damage 2 × Repeat 3 = 6 + bonus"},
    "CELESTIAL_MIGHT":     {"value": 18, "basis": "Damage 6 × Repeat 3 = 18 cost 2"},
    "GUNK_UP":             {"value": 12, "basis": "Damage 4 × Repeat 3 = 12 cost 1"},
    "RICOCHET":            {"value": 14, "basis": "Damage 3 × Repeat 4 = 12 cost 2 + scaling"},
    "SPITE":               {"value": 12, "basis": "Damage 5 × Repeat 2 = 10 cost 0 + bonus"},
    "REFRACT":             {"value": 18, "basis": "Damage 9 × Repeat 2 = 18 cost 3"},
    "ICE_LANCE":           {"value": 28, "ceiling": 50, "basis": "Damage 19 × Repeat 3 = 57 cost 3 / use 0.5 = 28 (boss kill)", "ceiling_basis": "FROST/ORB 빌드 boss — 19 × Repeat 3 = 57 × focus 보강 + 사용 1회 보장"},
    "SEVEN_STARS":         {"value": 32, "ceiling": 55, "basis": "Damage 7 × Repeat 7 = 49 cost 2 + star 7 (huge attack)", "ceiling_basis": "REGENT 별 충분 시 — Damage 7 × Repeat 7 = 49 × STR/취약 보강 = 70+, 다회 사용 시"},
    "CONSUMING_SHADOW":    {"value": 16, "ceiling": 35, "basis": "ConsumingShadowPower × Repeat 2 cumulative scaling", "ceiling_basis": "Power 빌드 + 8턴 — ConsumingShadowPower 누적 × Repeat 2 × multi-cast"},
    "DEATHS_DOOR":         {"value": 12, "basis": "Block 6 × Repeat 2 = 12 cost 1"},
    "DECISIONS_DECISIONS": {"value": 14, "basis": "Cards 3 × Repeat 3 = 9 + EXHAUST cost 0"},
    "FIGHT_ME":            {"value": 22, "basis": "Damage 5 × Repeat 2 = 10 + STR + EnemyStr cost 2"},

    "_cost_enabler_comment": "비용 무관 사용 카드 — 다음 카드 cost 0 또는 자체 cost 무관",

    "UNRELENTING":         {"value": 14, "basis": "Damage 12 + 다음 attack cost 0 = 12 + ~6 cost saved"},
    "HAVOC":               {"value": 12, "basis": "draw + auto-play cost 0 — 다음 카드 cost 무관 사용"},
    "DOUBLE_TAP":          {"value": 16, "basis": "다음 attack ×2 — 8 dmg avg + 부가"},
    "BURST":               {"value": 14, "basis": "다음 skill ×2 — 6 block + scaling"},

    "_exhaust_comment": "EXHAUST_PRODUCER 카드 — 손 / 카드 소멸 trigger. vars 만으로 mechanic 못 잡음.",

    "FIEND_FIRE":          {"value": 22, "ceiling": 45, "basis": "지옥불 — Damage 7 × hand exhaust 5장 = 35 cost 2 / use 1.5", "ceiling_basis": "EXHAUST_BURST 빌드 — full hand 8장 × 7 dmg = 56 × STR/취약 보강"},
    "PURITY":              {"value": 12, "basis": "순수 — Cards 3 + exhaust 1~3 cost 0"},
    "SECOND_WIND":         {"value": 12, "basis": "기사회생 — Block 5 × hand size 5 cost 1"},
    "TRUE_GRIT":           {"value": 10, "basis": "진정한 끈기 — Block 7 + exhaust random cost 1"},
    "EIDOLON":             {"value": 14, "basis": "허상 — EXHAUST_BURST hand 모두 cost 2"},
    "STOKE":               {"value": 14, "basis": "화력 증폭 — EXHAUST_BURST + 강화 cost 1"},
    "TYRANNY":             {"value": 14, "basis": "독재 — EXHAUST + scaling cost 1"},
    "CLEANSE":             {"value": 10, "basis": "정화 — Summon 3 + exhaust cost 1"},
    "BURNING_PACT":        {"value": 12, "basis": "불타는 조약 — Cards 2 × draw + exhaust 1 cost 1"},
    "CINDER":              {"value": 18, "basis": "잿불 — Damage 18 cost 2 + EXHAUST_PRODUCER"},
    "SCAVENGE":            {"value": 16, "basis": "포집 — Energy 2 + EXHAUST cost 1"},

    "_strength_comment": "StrengthPower 부여 카드 — vars scaling 환산은 적정. 단 일부 cost-effective 카드 fine-tune.",

    "COORDINATE":          {"value": 14, "basis": "협력 — StrengthPower 5 cost 1 + 조건부 (별 cost 보강)"},
    "FEEDING_FRENZY":      {"value": 18, "ceiling": 38, "basis": "광란의 포식 — StrengthPower 5 cost 0 단 SCALING/CONSUMER 의존", "ceiling_basis": "STR/SCALING 빌드 — STR 5 × 5+ atk/turn × 8 turn 누적, cost 0 multi-use 시"},
    "PROWESS":             {"value": 10, "basis": "기량 — STR 1 + DEX 1 cost 1"},
    "RESONANCE":           {"value": 8,  "basis": "공진 — StrengthPower 1 cost 1"},
    "RUPTURE":             {"value": 8,  "basis": "파열 — StrengthPower 1 cost 1 (HpLoss 시 trigger)"},
    "BRAND":               {"value": 8,  "basis": "낙인 — StrengthPower 1 cost 0 + HpLoss 1 (영구 STR)"},
    "FRIENDSHIP":          {"value": 16, "basis": "우정 — Energy 1 + StrengthPower 2 cost 1"},
    "BULK_UP":             {"value": 18, "basis": "증강 — DEX 2 + STR 2 + OrbSlot 1 cost 2"},
    "SETUP_STRIKE":        {"value": 16, "basis": "사전 타격 — Damage 7 + StrengthPower 2 (turn 한정) cost 1"},

    "_multihit_comment": "Multi-hit / 조건부 hit count 카드 — desc 의 hit 횟수가 vars 에 안 잡힘.",

    "TWIN_STRIKE":         {"value": 10, "basis": "이중 타격 — Damage 5 × 2 hits = 10 cost 1"},
    "DAGGER_SPRAY":        {"value": 12, "basis": "단검 분사 — Damage 4 × 2 hits AOE cost 1"},
    "TEAR_ASUNDER":        {"value": 18, "basis": "갈가리 찢기 — Damage 5 × hp_loss_count 평균 4 = 20 cost 2 / use 0.9"},
    "CLAW":                {"value": 10, "basis": "후벼 파기 — Damage 3 + Increase 2/play × 5 plays cost 0"},
    "MAUL":                {"value": 10, "basis": "할퀴기 — Damage 5 + Increase 1 누적"},
    "RAMPAGE":             {"value": 16, "basis": "광란 — Damage 9 + Increase 5/play (3~4 plays)"},
    "BALL_LIGHTNING":      {"value": 12, "basis": "번개 구체 — Damage 7 + lightning orb"},
    "SKEWER":              {"value": 14, "basis": "꼬챙이 — Damage 8 × X cost variable"},
    "VOLLEY":              {"value": 14, "basis": "난사 — Damage 10 × X cost AOE"},
    "STRANGLE":            {"value": 14, "basis": "목 조르기 — Damage 8 + StranglePower 누적"},
    "REBOUND":             {"value": 12, "basis": "되돌리기 — Damage 9 + Repeat 다음 turn"},
    "RIP_AND_TEAR":        {"value": 10, "basis": "날뛰기 — Damage 7 + multi-hit"},
    "GOLD_AXE":            {"value": 8,  "basis": "황금 도끼 — ExtraDamage 1 scaling × gold count"},
    "DUALCAST":            {"value": 14, "basis": "이중 시전 — orb evoke ×2 cost 1"},
    "MAD_SCIENCE":         {"value": 24, "basis": "괴짜 과학 — vars 11종 random burst cost 1 (large effect)"},

    "_cunning_comment": "CUNNING archetype — discard trigger 카드 의 vars 단순 환산이 trigger 효과 못 잡음.",

    "PREPARED":            {"value": 8,  "basis": "예비 — Cards 1 + discard 1 (CUNNING_CONSUMER trigger)"},
    "REFLEX":              {"value": 10, "basis": "반사신경 — Cards 2 (discard trigger 시 발동)"},
    "TACTICIAN":           {"value": 14, "basis": "전략가 — Energy 1 + discard trigger cost 3"},
    "ACROBATICS":          {"value": 12, "basis": "곡예 — Cards 3 + discard 1 cost 1"},
    "SHADOW_STEP":         {"value": 10, "basis": "그림자 걸음 — Cards 3 + discard cost 1"},
    "DAGGER_THROW":        {"value": 12, "basis": "단검 투척 — Damage 9 + discard cost 1"},
    "SCRAPE":              {"value": 14, "basis": "긁어내기 — Cards 4 + Damage 7 단 condition (~50% activate)"},
    "FLICK_FLACK":         {"value": 10, "basis": "재주넘기 — Damage 6 + CUNNING cost 1"},
    "HAND_TRICK":          {"value": 10, "basis": "손기술 — Block 7 + CUNNING cost 1"},
    "HAZE":                {"value": 16, "basis": "아지랑이 — PoisonPower 4 cost 3 + CUNNING"},
    "HIDDEN_DAGGERS":      {"value": 14, "basis": "숨겨진 단검 — Cards 2 + Shivs 2 cost 0"},
    "ABRASIVE":            {"value": 18, "basis": "연마 — DEX 1 + Thorns 4 cost 3 (vars overestimate fix)"},
    "UNTOUCHABLE":         {"value": 12, "basis": "범접 불가 — Block 6 + CUNNING_PRODUCER cost 2"},
    "SURVIVOR":            {"value": 10, "basis": "생존자 — Block 8 + discard cost 1"},

    "_dyingstar_comment": "DYING_STAR / MANGLE 등 큰 vars overestimate — STR Loss factor 4 × 9~10 stacks 가 너무 큼. 진짜 mechanic (1 stack 적용 후 ↓) 반영.",

    "DYING_STAR":          {"value": 22, "basis": "Damage 9 + StrengthLoss 9 — 단 1 stack 적용 후 ↓ (vars 45 overestimate)"},
    "MANGLE":              {"value": 28, "basis": "Damage 15 + StrengthLoss 10 cost 3 (vars 55 overestimate)"},

    "_largex_comment": "X-cost / energy 큰 카드 vars overestimate fix",

    "BANSHEES_CRY":        {"value": 30, "basis": "Damage 33 + Energy 2 cost 9 — boss kill (vars 49 단 cost 9)"},
    "HEAVENLY_DRILL":      {"value": 24, "basis": "Damage 8 + Energy 4 cost 0 (vars 40 단 condition)"},
    "SUNDER":              {"value": 26, "basis": "Damage 24 + 처치 시 Energy 3 cost 3 (vars 48 conditional)"},

    "_pillage_comment": "조건부 + draw / 큰 effect 카드 — vars 가 Damage 만 단순 환산해 mechanic 못 잡음.",

    "PILLAGE":             {"value": 14, "basis": "갈취 — Damage 6 + 공격 카드 draw infinite (~3 attack draw)"},
    "ECHOING_SLASH":       {"value": 16, "basis": "메아리 참격 — Damage 10 AOE + 처치 시 반복"},
    "FISTICUFFS":          {"value": 14, "basis": "주먹다짐 — Damage 7 + 가한 피해만큼 Block 7"},
    "GRAND_FINALE":        {"value": 28, "ceiling": 55, "basis": "대단원의 막 — Damage 60 AOE 단 deck 압축 조건 어려움 (vars 60 overestimate)", "ceiling_basis": "deck-thinning + DRAW 빌드 — AOE 60 × 1.5 use × 1.2 multi-enemy, 조건 자체 보장 시"},
    "HEADBUTT":            {"value": 12, "basis": "박치기 — Damage 9 + discard recover 1 (cycle gain)"},
    "KINGLY_KICK":         {"value": 22, "basis": "왕의 발차기 — Damage 27 cost 4 (cost penalty)"},
    "PINPOINT":            {"value": 18, "basis": "정밀 사격 — Damage 15 + skill cost reduce condition"},
    "PREDATOR":            {"value": 18, "basis": "천적 — Damage 15 + 다음 turn draw 2"},
    "SCULPTING_STRIKE":    {"value": 12, "basis": "조각 타격 — Damage 9 + Volatile 부여"},
    "SEVERANCE":           {"value": 16, "basis": "분리 — Damage 13 + Soul 1 추가"},
    "TAG_TEAM":            {"value": 12, "basis": "태그 팀 — Damage 11 (multiplayer condition)"},
    "THE_HUNT":            {"value": 12, "basis": "사냥 — Damage 10 + 치명타 reward bonus"},
    "UPROAR":              {"value": 14, "basis": "난동 — Damage 5×2 + random attack draw"},
    "ANGER":                {"value": 10, "basis": "분노 — Damage 6 + discard 복사본 (cycle gain)"},
    "FOLLOW_THROUGH":      {"value": 12, "basis": "완수 — Damage 7 + CardCount 5 condition"},

    "_outlier_comment": "전반 검증 후 발견 outlier 카드 — Tier vs EV 일관성 보정.",

    "BURY":                {"value": 26, "basis": "Damage 52 cost 4 — vars 52 단 cost 4 큼 (use rate 0.5)"},
    "THE_GAMBIT":          {"value": 24, "basis": "Block 50 cost 0 단 self-kill 조건 위험 (vars 50 overestimate)"},
    "BUBBLE_BUBBLE":       {"value": 22, "basis": "Poison 9 단 poison 보유 조건 (vars 45 × 0.5 trigger)"},
    "KNOCKOUT_BLOW":       {"value": 26, "basis": "Damage 30 + Stars 5 (처치 시) cost 3"},
    "ETERNAL_ARMOR":       {"value": 22, "basis": "PlatingPower 9 cost 3 — scaling 보강"},
    "JACKPOT":             {"value": 28, "basis": "Damage 25 + cost 0 카드 3장 hand (vars 37 적정)"},
    "WHISTLE":             {"value": 24, "basis": "Damage 33 + 기절 cost 3 — 큰 cost"},
    "HYPERBEAM":           {"value": 24, "basis": "Damage 26 AOE + Focus 3 손실 cost 2"},
    "BLUDGEON":            {"value": 22, "basis": "Damage 32 cost 3 — 단순 큰 dmg"},
    "RELAX":               {"value": 28, "basis": "Block 15 + Cards 2 + Energy 2 cost 3 (다음 turn)"},
    "BREAK":               {"value": 30, "basis": "Damage 20 + Vuln 5 cost 1 (vars 40 적정 — 단 작은 보정)"},

    "_underestimate_comment": "S/A 등급 인데 EV 작은 카드 — 복합 mechanic vars 환산 부정확.",

    "ESCAPE_PLAN":         {"value": 12, "basis": "draw 1 + Block 3 (skill 50% trigger) cost 0 — S Tier"},
    "HOLOGRAM":            {"value": 14, "basis": "Block 3 + discard recover 1 + EXHAUST cost 1 — S Tier"},
    "DEATHBRINGER":        {"value": 22, "basis": "DoomPower 21 즉사 + Weak 1 cost 2 — S Tier (boss kill potential)"},
    "TESLA_COIL":          {"value": 12, "basis": "Damage 3 + 모든 lightning orb 발동 cost 0 (orb 의존)"},
    "DARK_SHACKLES":       {"value": 24, "basis": "DoomPower + 즉발 trigger cost 0 (vars 36 cost 0 fix)"}
  }
}
